Metadata-Version: 2.1
Name: kiddeemata
Version: 1.4.1
Summary: A Python Protocol Abstraction Library For Arduino Firmata - Updated by Kiddee Lab
Home-page: https://github.com/xavjb/kiddeemata
Author: Kiddee Lab
Author-email: kiddeelab2@gmail.com
License: UNKNOWN
Download-URL: https://github.com/xavjb/kiddeemata
Keywords: Firmata,Arduino,Protocol,Python,Kiddee Lab
Platform: UNKNOWN
Classifier: Development Status :: 5 - Production/Stable
Classifier: Environment :: Other Environment
Classifier: Intended Audience :: Developers
Classifier: Intended Audience :: Education
Classifier: License :: OSI Approved :: GNU Affero General Public License v3 or later (AGPLv3+)
Classifier: Operating System :: OS Independent
Classifier: Programming Language :: Python :: 3.7
Classifier: Programming Language :: Python :: 3.8
Classifier: Programming Language :: Python :: 3.9
Classifier: Topic :: Software Development :: Libraries :: Python Modules
